{"obstacle_mesh_path": "/root/catkin_ws/src/jiaming_manipulation/task_planner/mesh_dir/table_with_dinnerware.stl", "co_parameter2_index": 138, "foliation1_name": "pour", "obstacle_pose": [[0.0, 1.0, 0.0, 0.7], [-1.0, 0.0, 0.0, -0.4], [0.0, 0.0, 1.0, -0.02], [0.0, 0.0, 0.0, 1.0]], "object_mesh_path": "/root/catkin_ws/src/jiaming_manipulation/task_planner/mesh_dir/cup.stl", "motion": [[1.2812799674737787, 0.9330753540387824, 1.3235872265083635, -1.6238945297892495, 1.1957268914804784, -0.6527642510035322, 1.2558926425217924]], "co_parameter1_index": 138, "foliation2_name": "pick", "action": "grasp", "active_joints": ["shoulder_pan_joint", "shoulder_lift_joint", "upperarm_roll_joint", "elbow_flex_joint", "forearm_roll_joint", "wrist_flex_joint", "wrist_roll_joint"], "object_pose": [[1.0, 0.0, 0.0, 0.68], [0.0, 1.0, 0.0, 0.05], [0.0, 0.0, 1.0, 0.9], [0.0, 0.0, 0.0, 1.0]]}