{"obstacle_mesh_path": "/root/catkin_ws/src/jiaming_manipulation/task_planner/mesh_dir/table_with_dinnerware.stl", "co_parameter2_index": 37, "foliation1_name": "pour", "obstacle_pose": [[0.0, 1.0, 0.0, 0.7], [-1.0, 0.0, 0.0, -0.4], [0.0, 0.0, 1.0, -0.02], [0.0, 0.0, 0.0, 1.0]], "object_mesh_path": "/root/catkin_ws/src/jiaming_manipulation/task_planner/mesh_dir/cup.stl", "motion": [[-0.8611734857676794, -0.1471109286650551, 0.6847020842217156, 1.594884860675033, 1.1090257896841367, 0.7420136597742771, -0.37545359937218825]], "co_parameter1_index": 37, "foliation2_name": "place_1", "action": "release", "active_joints": ["shoulder_pan_joint", "shoulder_lift_joint", "upperarm_roll_joint", "elbow_flex_joint", "forearm_roll_joint", "wrist_flex_joint", "wrist_roll_joint"], "object_pose": [[1.0, 0.0, 0.0, 0.68], [0.0, -0.32328956686350363, -0.9463000876874148, 0.05], [0.0, 0.9463000876874148, -0.32328956686350363, 0.9], [0.0, 0.0, 0.0, 1.0]]}