{"obstacle_mesh_path": "/root/catkin_ws/src/jiaming_manipulation/task_planner/mesh_dir/table_with_dinnerware.stl", "co_parameter2_index": 51, "foliation1_name": "pick", "obstacle_pose": [[0.0, 1.0, 0.0, 0.7], [-1.0, 0.0, 0.0, -0.4], [0.0, 0.0, 1.0, -0.02], [0.0, 0.0, 0.0, 1.0]], "object_mesh_path": "/root/catkin_ws/src/jiaming_manipulation/task_planner/mesh_dir/cup.stl", "motion": [[-0.3546990200378472, 0.21029508072045103, -0.5522575832138874, 1.2933252851149173, -2.678227050288736, 1.2832353688553115, -2.6784625597370835]], "co_parameter1_index": 51, "foliation2_name": "init", "action": "grasp", "active_joints": ["shoulder_pan_joint", "shoulder_lift_joint", "upperarm_roll_joint", "elbow_flex_joint", "forearm_roll_joint", "wrist_flex_joint", "wrist_roll_joint"], "object_pose": [[1.0, 0.0, 0.0, 0.68], [0.0, 1.0, 0.0, -0.55], [0.0, 0.0, 1.0, 0.78], [0.0, 0.0, 0.0, 1.0]]}