{"obstacle_mesh_path": "/root/catkin_ws/src/jiaming_manipulation/task_planner/mesh_dir/table_with_dinnerware.stl", "co_parameter2_index": 1, "foliation1_name": "place_1", "obstacle_pose": [[0.0, 1.0, 0.0, 0.7], [-1.0, 0.0, 0.0, -0.4], [0.0, 0.0, 1.0, -0.02], [0.0, 0.0, 0.0, 1.0]], "object_mesh_path": "/root/catkin_ws/src/jiaming_manipulation/task_planner/mesh_dir/cup.stl", "motion": [[-0.26181035389754304, -0.13568314241266424, -1.7181230658814393, -0.5813738360095513, -1.0709735302193046, -1.4686091436092628, -1.2625250439032785]], "co_parameter1_index": 1, "foliation2_name": "place_2", "action": "release", "active_joints": ["shoulder_pan_joint", "shoulder_lift_joint", "upperarm_roll_joint", "elbow_flex_joint", "forearm_roll_joint", "wrist_flex_joint", "wrist_roll_joint"], "object_pose": [[1.0, 0.0, 0.0, 0.8], [0.0, -0.32328956686350363, -0.9463000876874148, 0.05], [0.0, 0.9463000876874148, -0.32328956686350363, 0.9], [0.0, 0.0, 0.0, 1.0]]}