{"obstacle_mesh_path": "/root/catkin_ws/src/jiaming_manipulation/task_planner/mesh_dir/table_with_dinnerware.stl", "co_parameter2_index": 158, "foliation1_name": "init", "obstacle_pose": [[0.0, 1.0, 0.0, 0.7], [-1.0, 0.0, 0.0, -0.4], [0.0, 0.0, 1.0, -0.02], [0.0, 0.0, 0.0, 1.0]], "object_mesh_path": "/root/catkin_ws/src/jiaming_manipulation/task_planner/mesh_dir/cup.stl", "motion": [[-0.49114301942288496, 0.022693805044573075, 0.43182964201907553, 0.3448428942882422, -1.2897724169332114, 1.2570275998165297, 1.7351551190907726]], "co_parameter1_index": 158, "foliation2_name": "pick", "action": "release", "active_joints": ["shoulder_pan_joint", "shoulder_lift_joint", "upperarm_roll_joint", "elbow_flex_joint", "forearm_roll_joint", "wrist_flex_joint", "wrist_roll_joint"], "object_pose": [[1.0, 0.0, 0.0, 0.68], [0.0, 1.0, 0.0, -0.55], [0.0, 0.0, 1.0, 0.78], [0.0, 0.0, 0.0, 1.0]]}