{"obstacle_mesh_path": "/root/catkin_ws/src/jiaming_manipulation/task_planner/mesh_dir/table_with_dinnerware.stl", "co_parameter2_index": 68, "foliation1_name": "pour", "obstacle_pose": [[0.0, 1.0, 0.0, 0.7], [-1.0, 0.0, 0.0, -0.4], [0.0, 0.0, 1.0, -0.02], [0.0, 0.0, 0.0, 1.0]], "object_mesh_path": "/root/catkin_ws/src/jiaming_manipulation/task_planner/mesh_dir/cup.stl", "motion": [[1.407511331411794, 1.0833627914857993, -1.34368759004252, 1.885445471031833, -2.588956879315202, 0.33134452745092224, -1.0094990962847683]], "co_parameter1_index": 68, "foliation2_name": "pick", "action": "grasp", "active_joints": ["shoulder_pan_joint", "shoulder_lift_joint", "upperarm_roll_joint", "elbow_flex_joint", "forearm_roll_joint", "wrist_flex_joint", "wrist_roll_joint"], "object_pose": [[1.0, 0.0, 0.0, 0.68], [0.0, 1.0, 0.0, 0.05], [0.0, 0.0, 1.0, 0.9], [0.0, 0.0, 0.0, 1.0]]}