{"obstacle_mesh_path": "/root/catkin_ws/src/jiaming_manipulation/task_planner/mesh_dir/table_with_dinnerware.stl", "co_parameter2_index": 161, "foliation1_name": "place_1", "obstacle_pose": [[0.0, 1.0, 0.0, 0.7], [-1.0, 0.0, 0.0, -0.4], [0.0, 0.0, 1.0, -0.02], [0.0, 0.0, 0.0, 1.0]], "object_mesh_path": "/root/catkin_ws/src/jiaming_manipulation/task_planner/mesh_dir/cup.stl", "motion": [[-0.6873806526265062, 0.057019611775039926, -2.188501691531082, -0.8432149201729803, 0.28624940609496313, -0.9939660934356129, -2.5035854858017275]], "co_parameter1_index": 161, "foliation2_name": "place_2", "action": "release", "active_joints": ["shoulder_pan_joint", "shoulder_lift_joint", "upperarm_roll_joint", "elbow_flex_joint", "forearm_roll_joint", "wrist_flex_joint", "wrist_roll_joint"], "object_pose": [[1.0, 0.0, 0.0, 0.8], [0.0, -0.32328956686350363, -0.9463000876874148, 0.05], [0.0, 0.9463000876874148, -0.32328956686350363, 0.9], [0.0, 0.0, 0.0, 1.0]]}