{"obstacle_mesh_path": "/root/catkin_ws/src/jiaming_manipulation/task_planner/mesh_dir/table_with_dinnerware.stl", "co_parameter2_index": 158, "foliation1_name": "place_1", "obstacle_pose": [[0.0, 1.0, 0.0, 0.7], [-1.0, 0.0, 0.0, -0.4], [0.0, 0.0, 1.0, -0.02], [0.0, 0.0, 0.0, 1.0]], "object_mesh_path": "/root/catkin_ws/src/jiaming_manipulation/task_planner/mesh_dir/cup.stl", "motion": [[0.5219748819475472, -0.36746447080437444, -0.3736312723836521, 1.3285431975207567, -0.9091391033315648, 0.4750670299153334, -1.1622168235104227]], "co_parameter1_index": 158, "foliation2_name": "pour", "action": "grasp", "active_joints": ["shoulder_pan_joint", "shoulder_lift_joint", "upperarm_roll_joint", "elbow_flex_joint", "forearm_roll_joint", "wrist_flex_joint", "wrist_roll_joint"], "object_pose": [[1.0, 0.0, 0.0, 0.8], [0.0, 1.0, 0.0, 0.05], [0.0, 0.0, 1.0, 0.78], [0.0, 0.0, 0.0, 1.0]]}