{"obstacle_mesh_path": "/root/catkin_ws/src/jiaming_manipulation/task_planner/mesh_dir/table_with_dinnerware.stl", "co_parameter2_index": 136, "foliation1_name": "pour", "obstacle_pose": [[0.0, 1.0, 0.0, 0.7], [-1.0, 0.0, 0.0, -0.4], [0.0, 0.0, 1.0, -0.02], [0.0, 0.0, 0.0, 1.0]], "object_mesh_path": "/root/catkin_ws/src/jiaming_manipulation/task_planner/mesh_dir/cup.stl", "motion": [[0.7838605184256305, 0.35841154811130344, -0.7634831868410404, 0.9086374464059787, -1.079162433351682, 0.9776550930426786, 2.6988089960414574]], "co_parameter1_index": 136, "foliation2_name": "place_1", "action": "release", "active_joints": ["shoulder_pan_joint", "shoulder_lift_joint", "upperarm_roll_joint", "elbow_flex_joint", "forearm_roll_joint", "wrist_flex_joint", "wrist_roll_joint"], "object_pose": [[1.0, 0.0, 0.0, 0.8], [0.0, 1.0, 0.0, 0.05], [0.0, 0.0, 1.0, 0.78], [0.0, 0.0, 0.0, 1.0]]}