{"obstacle_mesh_path": "/root/catkin_ws/src/jiaming_manipulation/task_planner/mesh_dir/table_with_dinnerware.stl", "co_parameter2_index": 176, "foliation1_name": "pour", "obstacle_pose": [[0.0, 1.0, 0.0, 0.7], [-1.0, 0.0, 0.0, -0.4], [0.0, 0.0, 1.0, -0.02], [0.0, 0.0, 0.0, 1.0]], "object_mesh_path": "/root/catkin_ws/src/jiaming_manipulation/task_planner/mesh_dir/cup.stl", "motion": [[0.6034003876006653, -0.1686108890205211, -0.31317749074711704, 2.1262623617007073, 0.7318019728027885, -1.637260926623518, -2.662306464098757]], "co_parameter1_index": 176, "foliation2_name": "pick", "action": "grasp", "active_joints": ["shoulder_pan_joint", "shoulder_lift_joint", "upperarm_roll_joint", "elbow_flex_joint", "forearm_roll_joint", "wrist_flex_joint", "wrist_roll_joint"], "object_pose": [[1.0, 0.0, 0.0, 0.68], [0.0, 1.0, 0.0, 0.05], [0.0, 0.0, 1.0, 0.9], [0.0, 0.0, 0.0, 1.0]]}