{"obstacle_mesh_path": "/root/catkin_ws/src/jiaming_manipulation/task_planner/mesh_dir/table_with_dinnerware.stl", "co_parameter2_index": 137, "foliation1_name": "pour", "obstacle_pose": [[0.0, 1.0, 0.0, 0.7], [-1.0, 0.0, 0.0, -0.4], [0.0, 0.0, 1.0, -0.02], [0.0, 0.0, 0.0, 1.0]], "object_mesh_path": "/root/catkin_ws/src/jiaming_manipulation/task_planner/mesh_dir/cup.stl", "motion": [[-0.8022248957886838, -0.23410737377029078, -1.8167438400683604, -1.8952645190851931, 1.2436575407989776, 0.7654501594156999, -0.17091949011921756]], "co_parameter1_index": 137, "foliation2_name": "place_1", "action": "release", "active_joints": ["shoulder_pan_joint", "shoulder_lift_joint", "upperarm_roll_joint", "elbow_flex_joint", "forearm_roll_joint", "wrist_flex_joint", "wrist_roll_joint"], "object_pose": [[1.0, 0.0, 0.0, 0.68], [0.0, -0.32328956686350363, -0.9463000876874148, 0.05], [0.0, 0.9463000876874148, -0.32328956686350363, 0.9], [0.0, 0.0, 0.0, 1.0]]}