{"obstacle_mesh_path": "/root/catkin_ws/src/jiaming_manipulation/task_planner/mesh_dir/table_with_dinnerware.stl", "co_parameter2_index": 147, "foliation1_name": "place_1", "obstacle_pose": [[0.0, 1.0, 0.0, 0.7], [-1.0, 0.0, 0.0, -0.4], [0.0, 0.0, 1.0, -0.02], [0.0, 0.0, 0.0, 1.0]], "object_mesh_path": "/root/catkin_ws/src/jiaming_manipulation/task_planner/mesh_dir/cup.stl", "motion": [[-0.357896534848869, -0.741503599918828, -2.667482319655006, -1.7414750687987504, -3.141244641413814, 0.07781548316236894, 1.5434995376386307]], "co_parameter1_index": 147, "foliation2_name": "place_2", "action": "release", "active_joints": ["shoulder_pan_joint", "shoulder_lift_joint", "upperarm_roll_joint", "elbow_flex_joint", "forearm_roll_joint", "wrist_flex_joint", "wrist_roll_joint"], "object_pose": [[1.0, 0.0, 0.0, 0.75], [0.0, -0.32328956686350363, -0.9463000876874148, 0.05], [0.0, 0.9463000876874148, -0.32328956686350363, 0.9], [0.0, 0.0, 0.0, 1.0]]}