{"obstacle_mesh_path": "/root/catkin_ws/src/jiaming_manipulation/task_planner/mesh_dir/table_with_dinnerware.stl", "co_parameter2_index": 109, "foliation1_name": "pour", "obstacle_pose": [[0.0, 1.0, 0.0, 0.6], [-1.0, 0.0, 0.0, -0.2], [0.0, 0.0, 1.0, -0.02], [0.0, 0.0, 0.0, 1.0]], "object_mesh_path": "/root/catkin_ws/src/jiaming_manipulation/task_planner/mesh_dir/cup.stl", "motion": [[-5.938442223613188, -4.80101523988975, -2.0024910820622117, 3.88337962696571, 4.448126619675384, -1.174922522468585]], "co_parameter1_index": 109, "foliation2_name": "place_1", "action": "release", "active_joints": ["shoulder_pan_joint", "shoulder_lift_joint", "elbow_joint", "wrist_1_joint", "wrist_2_joint", "wrist_3_joint"], "object_pose": [[1.0, 0.0, 0.0, 0.58], [0.0, -0.32328956686350363, -0.9463000876874148, 0.25], [0.0, 0.9463000876874148, -0.32328956686350363, 0.9], [0.0, 0.0, 0.0, 1.0]]}