{"obstacle_mesh_path": "/root/catkin_ws/src/jiaming_manipulation/task_planner/mesh_dir/table_with_dinnerware.stl", "co_parameter2_index": 21, "foliation1_name": "pick", "obstacle_pose": [[0.0, 1.0, 0.0, 0.9], [-1.0, 0.0, 0.0, 0.0], [0.0, 0.0, 1.0, -0.02], [0.0, 0.0, 0.0, 1.0]], "object_mesh_path": "/root/catkin_ws/src/jiaming_manipulation/task_planner/mesh_dir/cup.stl", "motion": [[-2.962648590630409, -3.867246955704449, 1.013106611856243, -3.4290452274818644, 5.640933236149176, 3.1415926671282963]], "co_parameter1_index": 21, "foliation2_name": "init", "action": "grasp", "active_joints": ["shoulder_pan_joint", "shoulder_lift_joint", "elbow_joint", "wrist_1_joint", "wrist_2_joint", "wrist_3_joint"], "object_pose": [[1.0, 0.0, 0.0, 0.88], [0.0, 1.0, 0.0, -0.15], [0.0, 0.0, 1.0, 0.78], [0.0, 0.0, 0.0, 1.0]]}