{"obstacle_mesh_path": "/root/catkin_ws/src/jiaming_manipulation/task_planner/mesh_dir/table_with_dinnerware.stl", "co_parameter2_index": 214, "foliation1_name": "init", "obstacle_pose": [[0.0, 1.0, 0.0, 0.9], [-1.0, 0.0, 0.0, 0.0], [0.0, 0.0, 1.0, -0.02], [0.0, 0.0, 0.0, 1.0]], "object_mesh_path": "/root/catkin_ws/src/jiaming_manipulation/task_planner/mesh_dir/cup.stl", "motion": [[-0.29150901622471814, -6.018942683635446, -0.49575195584050585, 4.943821925217557, 4.7123622409494725, -5.039704259145155]], "co_parameter1_index": 214, "foliation2_name": "pick", "action": "release", "active_joints": ["shoulder_pan_joint", "shoulder_lift_joint", "elbow_joint", "wrist_1_joint", "wrist_2_joint", "wrist_3_joint"], "object_pose": [[1.0, 0.0, 0.0, 0.88], [0.0, 1.0, 0.0, -0.15], [0.0, 0.0, 1.0, 0.78], [0.0, 0.0, 0.0, 1.0]]}