{"obstacle_mesh_path": "/root/catkin_ws/src/jiaming_manipulation/task_planner/mesh_dir/table_with_dinnerware.stl", "co_parameter2_index": 194, "foliation1_name": "pick", "obstacle_pose": [[0.0, 1.0, 0.0, 0.7], [-1.0, 0.0, 0.0, -0.4], [0.0, 0.0, 1.0, -0.02], [0.0, 0.0, 0.0, 1.0]], "object_mesh_path": "/root/catkin_ws/src/jiaming_manipulation/task_planner/mesh_dir/cup.stl", "motion": [[0.36681237076315437, -0.16346105069078706, 3.141592103334428, -2.1148410304338436, 0.627655729709449, 1.8839900372881566, 0.21989052751954666]], "co_parameter1_index": 194, "foliation2_name": "pour", "action": "release", "active_joints": ["shoulder_pan_joint", "shoulder_lift_joint", "upperarm_roll_joint", "elbow_flex_joint", "forearm_roll_joint", "wrist_flex_joint", "wrist_roll_joint"], "object_pose": [[1.0, 0.0, 0.0, 0.68], [0.0, 1.0, 0.0, 0.05], [0.0, 0.0, 1.0, 0.9], [0.0, 0.0, 0.0, 1.0]]}